jasmine_zinc/Avatar.py
jasmine_zinc/Talk.py
jasmine_zinc/__init__.py
jasmine_zinc/add_talk_arguments.py
jasmine_zinc/get_avatars.py
jasmine_zinc/record_talk.py
jasmine_zinc/talk_on_server.py
jasmine_zinc/scripts/__init__.py
jasmine_zinc/scripts/get_avatars.py
jasmine_zinc/scripts/record_talk.py
jasmine_zinc/scripts/talk_on_server.py
jasmine_zinc-20210903.14.dist-info/LICENSE
jasmine_zinc-20210903.14.dist-info/METADATA
jasmine_zinc-20210903.14.dist-info/WHEEL
jasmine_zinc-20210903.14.dist-info/entry_points.txt
jasmine_zinc-20210903.14.dist-info/top_level.txt
jasmine_zinc-20210903.14.dist-info/RECORD
