Metadata-Version: 2.1
Name: jasmine-zinc
Version: 20210903.14
Summary: UNKNOWN
Home-page: https://github.com/aoirint/jasmine_zinc
Author: aoirint
Author-email: aoirint@gmail.com
License: MIT
Platform: UNKNOWN
Classifier: Development Status :: 3 - Alpha
Classifier: License :: OSI Approved :: MIT License
Classifier: Programming Language :: Python
Classifier: Programming Language :: Python :: 3
Classifier: Programming Language :: Python :: 3.6
Classifier: Programming Language :: Python :: 3.7
Classifier: Programming Language :: Python :: 3.8
Classifier: Programming Language :: Python :: 3.9
Requires-Dist: requests
Requires-Dist: playsound
